odoo8_addon_account_advanced_reconcile-8.0.1.0.0-py2.7-nspkg.pth
odoo_addons/account_advanced_reconcile/easy_reconcile_view.xml
odoo_addons/account_advanced_reconcile/__openerp__.py
odoo_addons/account_advanced_reconcile/res_config_view.xml
odoo_addons/account_advanced_reconcile/__init__.py
odoo_addons/account_advanced_reconcile/README.rst
odoo_addons/account_advanced_reconcile/models/res_config.py
odoo_addons/account_advanced_reconcile/models/base_advanced_reconciliation.py
odoo_addons/account_advanced_reconcile/models/easy_reconcile.py
odoo_addons/account_advanced_reconcile/models/__init__.py
odoo_addons/account_advanced_reconcile/models/advanced_reconciliation.py
odoo_addons/account_advanced_reconcile/i18n/account_advanced_reconcile.pot
odoo_addons/account_advanced_reconcile/i18n/es.po
odoo_addons/account_advanced_reconcile/i18n/fr.po
odoo8_addon_account_advanced_reconcile-8.0.1.0.0.dist-info/top_level.txt
odoo8_addon_account_advanced_reconcile-8.0.1.0.0.dist-info/WHEEL
odoo8_addon_account_advanced_reconcile-8.0.1.0.0.dist-info/RECORD
odoo8_addon_account_advanced_reconcile-8.0.1.0.0.dist-info/metadata.json
odoo8_addon_account_advanced_reconcile-8.0.1.0.0.dist-info/DESCRIPTION.rst
odoo8_addon_account_advanced_reconcile-8.0.1.0.0.dist-info/METADATA
odoo8_addon_account_advanced_reconcile-8.0.1.0.0.dist-info/namespace_packages.txt
