Metadata-Version: 2.0
Name: odoo8-addon-account-advanced-reconcile
Version: 8.0.1.0.0
Summary: Reconcile: with multiple lines / partial / with writeoffs
Home-page: http://www.camptocamp.com
Author: UNKNOWN
Author-email: UNKNOWN
License: AGPL-3
Platform: UNKNOWN
Requires-Dist: odoo (<9.0a,>=8.0a)
Requires-Dist: odoo8-addon-account-easy-reconcile
Classifier: Programming Language :: Python :: 2.7
Classifier: Framework :: Odoo
Classifier: License :: OSI Approved :: GNU Affero General Public License v3
